purse/__init__.py
purse/collections.py
purse/py.typed
purse/redlock.py
redis_purse-2.0.2.dist-info/LICENSE
redis_purse-2.0.2.dist-info/METADATA
redis_purse-2.0.2.dist-info/WHEEL
redis_purse-2.0.2.dist-info/RECORD
