Metadata-Version: 2.1
Name: redis-purse
Version: 2.0.2
Summary: High Level Asyncio interface to redis
Home-page: https://plataux.com
License: Apache-2.0
Keywords: key-value,caching,messaging
Author: mk
Author-email: mk@plataux.com
Requires-Python: >=3.8,<4
Classifier: License :: OSI Approved :: Apache Software License
Classifier: Operating System :: OS Independent
Classifier: Programming Language :: Python :: 3
Classifier: Programming Language :: Python :: 3.8
Classifier: Programming Language :: Python :: 3.9
Classifier: Programming Language :: Python :: 3.10
Classifier: Programming Language :: Python :: 3.11
Classifier: Topic :: Software Development :: Build Tools
Classifier: Topic :: Software Development :: Libraries :: Python Modules
Requires-Dist: pydantic (>=2,<3)
Requires-Dist: redis (>=5,<6)
Project-URL: Repository, https://github.com/plataux/purse
